sqltest/__init__.py
sqltest/datasource/__init__.py
sqltest/datasource/reader.py
sqltest/datasource/csv/__init__.py
sqltest/datasource/csv/csv_reader.py
sqltest/datasource/excel/__init__.py
sqltest/datasource/excel/excel_reader.py
sqltest/engine/__init__.py
sqltest/engine/engine.py
sqltest/engine/spark/__init__.py
sqltest/engine/spark/spark_engine.py
sqltest/marker/__init__.py
sqltest/marker/engine.py
sqltest/marker/reader.py
sqltest/parser/__init__.py
sqltest/parser/catalog.py
sqltest/parser/exceptions.py
sqltest/parser/operation.py
sqltest/parser/sql_extractor.py
sqltest/parser/sql_reader.py
sqltest/parser/strategy.py
sqltest/tools/__init__.py
sqltest/tools/dataframe_comparator.py
sqltest-0.0.14.dist-info/LICENSE
sqltest-0.0.14.dist-info/METADATA
sqltest-0.0.14.dist-info/WHEEL
sqltest-0.0.14.dist-info/top_level.txt
sqltest-0.0.14.dist-info/RECORD
