Metadata-Version: 2.1
Name: sqltest
Version: 0.0.14
Summary: sqltest: easy testing ETL sqls
Home-page: https://github.com/stayrascal/sqltest
Author: stayrascal
Author-email: stayrascal@gmail.com
License: MIT
Project-URL: Bug Tracker, https://github.com/stayrascal/sqltest/issues
Project-URL: Source Code, https://github.com/stayrascal/sqltest
Keywords: test,ETL,sql
Platform: UNKNOWN
Classifier: License :: OSI Approved :: MIT License
Classifier: Operating System :: OS Independent
Classifier: Programming Language :: Python :: 3
Classifier: Programming Language :: Python :: 3 :: Only
Classifier: Programming Language :: Python :: 3.6
Classifier: Programming Language :: Python :: 3.7
Classifier: Programming Language :: Python :: 3.8
Classifier: Programming Language :: Python :: 3.9
Classifier: Programming Language :: Python :: 3.10
Requires-Python: >=3.6
Requires-Dist: openpyxl (>=3.0.9)
